bcam/__init__.py
bcam/bcam.py
bcam/config.py
bcam/stitcher.py
bcam/utils.py
bcam-0.0.9.dist-info/LICENSE
bcam-0.0.9.dist-info/METADATA
bcam-0.0.9.dist-info/WHEEL
bcam-0.0.9.dist-info/top_level.txt
bcam-0.0.9.dist-info/RECORD
