Metadata-Version: 2.1
Name: bcam
Version: 0.0.9
Summary: An easy to use camera interface for NVIDIA Jetson and raspberry pi
Home-page: UNKNOWN
Author: Kevin Peng, Billy Wang
License: UNKNOWN
Platform: UNKNOWN
Classifier: Programming Language :: Python :: 3
Classifier: License :: OSI Approved :: MIT License
Classifier: Operating System :: OS Independent
Requires-Python: >=3.6
Requires-Dist: ipywidgets
Requires-Dist: imutils
